{"cameraMode":{"drawMode":2,"name":"Shaded Wireframe","section":"Shading Mode"},"sceneLighting":false,"audioPlay":false,"sceneViewState":{"m_AlwaysRefresh":false,"showFog":true,"showSkybox":false,"showFlares":true,"showImageEffects":true,"showParticleSystems":true,"showVisualEffectGraphs":true,"m_FxEnabled":true},"in2DMode":false,"pivot":{"x":-9.803180694580079,"y":-3.7806382179260256,"z":13.782804489135743},"rotation":{"x":0.7060452699661255,"y":8.82284911796205e-9,"z":-3.9517034089442406e-10,"w":0.7081664800643921},"size":21.92603302001953,"orthographic":true}